pantex/__init__.py
pantex/edit.py
pantex/publish.py
panTeX-0.0.9.dist-info/METADATA
panTeX-0.0.9.dist-info/WHEEL
panTeX-0.0.9.dist-info/top_level.txt
panTeX-0.0.9.dist-info/RECORD
