Metadata-Version: 2.1
Name: panTeX
Version: 0.0.9
Summary: Quickly build beautiful LaTeX documents from python/pandas
Home-page: https://github.com/pypa/sampleproject
Author: The Python Packaging Authority
License: UNKNOWN
Project-URL: Bug Reports, https://github.com/pypa/sampleproject/issues
Project-URL: Funding, https://donate.pypi.org
Project-URL: Say Thanks!, http://saythanks.io/to/example
Project-URL: Source, https://github.com/pypa/sampleproject/
Platform: UNKNOWN
Classifier: Development Status :: 3 - Alpha
Classifier: Intended Audience :: Developers
Classifier: Topic :: Software Development :: Build Tools
Classifier: License :: OSI Approved :: MIT License
Classifier: Programming Language :: Python :: 3.6
Classifier: Programming Language :: Python :: 3.7
Classifier: Programming Language :: Python :: 3.8
Classifier: Programming Language :: Python :: 3.9
Requires-Python: >=3.6, <4
Requires-Dist: pandas (>=1.0.0)
Requires-Dist: seaborn
Requires-Dist: altair
Requires-Dist: altair-saver
Requires-Dist: tabulate
Requires-Dist: typing-extensions
Provides-Extra: dev
Requires-Dist: ipython ; extra == 'dev'
Requires-Dist: pytest ; extra == 'dev'
